p4cmd/__init__.py
p4cmd/p4cmd.py
p4cmd/p4errors.py
p4cmd/p4file.py
p4cmd/utils.py
p4cmd/resources/__init__.py
p4cmd/resources/perforce_DEPOT_ONLY.png
p4cmd/resources/perforce_MOVED.png
p4cmd/resources/perforce_NEED_SYNC.png
p4cmd/resources/perforce_OPEN_FOR_ADD.png
p4cmd/resources/perforce_OPEN_FOR_DELETE.png
p4cmd/resources/perforce_OPEN_FOR_EDIT.png
p4cmd/resources/perforce_UNKNOWN.png
p4cmd/resources/perforce_UNTRACKED.png
p4cmd/resources/perforce_UP_TO_DATE.png
p4cmd-2.8.5.dist-info/licenses/LICENSE
p4cmd-2.8.5.dist-info/METADATA
p4cmd-2.8.5.dist-info/WHEEL
p4cmd-2.8.5.dist-info/top_level.txt
p4cmd-2.8.5.dist-info/RECORD
