Metadata-Version: 2.4
Name: p4cmd
Version: 2.8.5
Summary: Simple P4 python module
Home-page: https://github.com/nielsvaes/p4cmd
Author: Niels Vaes
Author-email: nielsvaes@gmail.com
License: MIT
Classifier: Operating System :: OS Independent
License-File: LICENSE
Dynamic: author
Dynamic: author-email
Dynamic: classifier
Dynamic: description
Dynamic: description-content-type
Dynamic: home-page
Dynamic: license
Dynamic: license-file
Dynamic: summary
